cmc_dataeng_internship_GaelleGreiveldinger/__init__.py
cmc_dataeng_internship_GaelleGreiveldinger/exercise13.py
cmc_dataeng_internship_GaelleGreiveldinger-0.1.2.dist-info/METADATA
cmc_dataeng_internship_GaelleGreiveldinger-0.1.2.dist-info/WHEEL
cmc_dataeng_internship_GaelleGreiveldinger-0.1.2.dist-info/top_level.txt
cmc_dataeng_internship_GaelleGreiveldinger-0.1.2.dist-info/RECORD
