Metadata-Version: 2.1
Name: cmc-dataeng-internship-GaelleGreiveldinger
Version: 0.1.2
Summary: Package for cmc_dataeng_internship_exercise
Home-page: UNKNOWN
Author: Gaëlle Greiveldinger
License: MIT
Platform: UNKNOWN
